COPYING.GPL
COPYING.LESSER
COPYING.PEXPECT
COPYING.WTFPL
MANIFEST.in
requirements.txt
setup.cfg
setup.py
ail/__init__.py
ail/base.py
ail/util.py
ail.egg-info/PKG-INFO
ail.egg-info/SOURCES.txt
ail.egg-info/dependency_links.txt
ail.egg-info/requires.txt
ail.egg-info/top_level.txt
ail/platforms/__init__.py
ail/platforms/templates.py
ail/platforms/cloudstream/__init__.py
ail/platforms/cloudstream/connected_clients.py
ail/platforms/cloudstream/cron_log.py
ail/platforms/cloudstream/platform.py
ail/platforms/cloudstream/server_status.py
ail/platforms/equallogic/__init__.py
ail/platforms/equallogic/add_volume_ace.py
ail/platforms/equallogic/parse_show.py
ail/platforms/equallogic/platform.py
ail/platforms/equallogic/set_environment.py
ail/platforms/equallogic/volume_acl.py
ail/platforms/equallogic/volumes.py
ail/platforms/linux/__init__.py
ail/platforms/linux/active_users.py
ail/platforms/linux/distribution.py
ail/platforms/linux/failed_logins.py
ail/platforms/linux/groups.py
ail/platforms/linux/hostname.py
ail/platforms/linux/kernel.py
ail/platforms/linux/last_logins.py
ail/platforms/linux/logins.py
ail/platforms/linux/mounts.py
ail/platforms/linux/netstats.py
ail/platforms/linux/packages.py
ail/platforms/linux/platform.py
ail/platforms/linux/processes.py
ail/platforms/linux/sshd_permit_root.py
ail/platforms/linux/sudo_logs.py
ail/platforms/linux/users.py
ail/services/__init__.py
ail/services/snmp.py
ail/services/ssh.py
ail/services/telnet.py
ail/tests/__init__.py
ail/tests/test_imports.py
ail/tests/test_parse_show.py