Metadata-Version: 1.1
Name: ail
Version: 0.2.7
Summary: abstract interaction layer
Home-page: https://github.com/jeandesmorts/ail
Author: jdmorts
Author-email: jean.des.morts@gmail.com
License: WTFPLv2
Keywords: automation
Platform: UNKNOWN
Classifier: License :: Public Domain
Classifier: Programming Language :: Python
Classifier: Development Status :: 2 - Pre-Alpha
Classifier: Intended Audience :: Information Technology
Classifier: Topic :: Software Development :: Libraries :: Application Frameworks
